statshog/__init__.py
statshog/tests.py
statshog/client/__init__.py
statshog/client/base.py
statshog/client/stream.py
statshog/client/timer.py
statshog/client/udp.py
statshog/defaults/__init__.py
statshog/defaults/django.py
statshog/defaults/env.py
statshog-1.0.6.dist-info/LICENSE
statshog-1.0.6.dist-info/METADATA
statshog-1.0.6.dist-info/WHEEL
statshog-1.0.6.dist-info/top_level.txt
statshog-1.0.6.dist-info/RECORD
